{
  "packages": [
    {
      "name": "thomas_spacemouse",
      "maintainer": "Thomas Sundberg",
      "websiteURL": "https://github.com/twprintsstudio/SpaceMouseAvr",
      "platforms": [
        {
          "name": "SpaceMouse Leonardo Board",
          "architecture": "avr",
          "version": "1.0.1",
          "category": "Contributed",
          "url": "https://github.com/twprintsstudio/SpaceMouseAvr/releases/download/v1.0.1/spacemouse-1.0.1.tar.bz2",
          "archiveFileName": "spacemouse-1.0.1.tar.bz2",
          "checksum": "SHA-256:b49013e8e92ebe61b5d5ea1a7d8bd03d44b031709c4ca517ba77faf9c5889c8c",
          "size": "7258424",
          "help": {
            "online": "https://github.com/twprintsstudio/SpaceMouseAvr/issues"
          },
          "boards": [
            { "name": "Spacemouse" }
          ],
          "toolsDependencies": []
        }
      ],
      "tools": []
    }
  ]
}
